{
  "title": "CALOFIC COMPETITOR REPORT",
  "subtitle": "PR & SOCIAL MONTHLY REPORT",
  "overall_summary": {
    "thoi_gian_trich_xuat": "Từ ngày 04/05/2025 đến ngày 04/07/2025",
    "industries": [
      {
        "nganh_hang": "Dầu ăn",
        "nhan_hang": [],
        "cum_noi_dung": [
          "Khác"
        ],
        "so_luong_bai": 8,
        "cac_dau_bao": [
          "EVA",
          "AFAMILY",
          "THANHNIENONLINE",
          "DOANHNHANSAIGON",
          "NONGNGHIEPONLINE",
          "SAIGONTIMESONLINE",
          "24H"
        ]
      }
    ],
    "tong_so_bai": 8
  },
  "industry_summaries": [
    {
      "nganh_hang": "Dầu ăn",
      "nhan_hang": [],
      "cum_noi_dung": [
        "Khác"
      ],
      "so_luong_bai": 8,
      "cac_dau_bao": [
        "EVA",
        "AFAMILY",
        "THANHNIENONLINE",
        "DOANHNHANSAIGON",
        "NONGNGHIEPONLINE",
        "SAIGONTIMESONLINE",
        "24H"
      ]
    }
  ],
  "articles": [
    {
      "stt": 1,
      "ngay_phat_hanh": "2025-07-04",
      "dau_bao": "SAIGONTIMESONLINE",
      "cum_noi_dung": "Khác",
      "tom_tat_noi_dung": "Không có bài viết nào trên trang https://thesaigontimes.vn chứa từ khóa \"dầu thực vật\", \"Nakydaco\", \"Nortalic\", \"Coba\" hoặc \"dầu hướng dương\" được đăng trong khoảng thời gian từ ngày 2025-05-04 đến ngày 2025-07-04.",
      "link_bai_bao": "https://thesaigontimes.vn",
      "nganh_hang": "Dầu ăn",
      "nhan_hang": [],
      "keywords_found": [],
      "crawl_timestamp": "2025-07-04T11:26:13.183515"
    },
    {
      "stt": 1,
      "ngay_phat_hanh": "2025-07-04",
      "dau_bao": "24H",
      "cum_noi_dung": "Khác",
      "tom_tat_noi_dung": "Không tìm thấy bài viết nào trên trang https://24h.com.vn liên quan đến các từ khóa \"dầu thực vật, Nakydaco, Nortalic, Coba, dầu hướng dương\" trong khoảng thời gian từ 2025-05-04 đến 2025-07-04.",
      "link_bai_bao": "https://24h.com.vn",
      "nganh_hang": "Dầu ăn",
      "nhan_hang": [],
      "keywords_found": [],
      "crawl_timestamp": "2025-07-04T11:26:12.309145"
    },
    {
      "stt": 1,
      "ngay_phat_hanh": "2025-07-04",
      "dau_bao": "EVA",
      "cum_noi_dung": "Khác",
      "tom_tat_noi_dung": "Không có bài viết nào dưới các từ khóa \"dầu thực vật\", \"Nakydaco\", \"Nortalic\", \"Coba\", \"dầu hướng dương\" trên website https://eva.vn trong khoảng thời gian từ ngày 2025-05-04 đến 2025-07-04.",
      "link_bai_bao": "https://eva.vn",
      "nganh_hang": "Dầu ăn",
      "nhan_hang": [],
      "keywords_found": [],
      "crawl_timestamp": "2025-07-04T11:26:19.935850"
    },
    {
      "stt": 1,
      "ngay_phat_hanh": "2025-07-04",
      "dau_bao": "THANHNIENONLINE",
      "cum_noi_dung": "Khác",
      "tom_tat_noi_dung": "Hiện tại tôi không thể lấy được thông tin từ trang web Thanh Niên qua việc tìm kiếm từ khóa. Tuy nhiên, bạn có thể tự kiểm tra trực tiếp trên trang web [thanhnien.vn] để tìm kiếm các bài báo có liên quan đến các từ khóa \"dầu thực vật, Nakydaco, Nortalic, Coba, dầu hướng dương\".",
      "link_bai_bao": "https://thanhnien.vn",
      "nganh_hang": "Dầu ăn",
      "nhan_hang": [],
      "keywords_found": [],
      "crawl_timestamp": "2025-07-04T11:26:27.528165"
    },
    {
      "stt": 1,
      "ngay_phat_hanh": "2025-07-04",
      "dau_bao": "NONGNGHIEPONLINE",
      "cum_noi_dung": "Khác",
      "tom_tat_noi_dung": "Không có bài viết nào được tìm thấy trên website https://nongnghiepmoitruong.vn mà phù hợp với các từ khóa \"dầu thực vật\", \"Nakydaco\", \"Nortalic\", \"Coba\", \"dầu hướng dương\" trong thời gian từ ngày 2025-05-04 đến ngày 2025-07-04.",
      "link_bai_bao": "https://nongnghiepmoitruong.vn",
      "nganh_hang": "Dầu ăn",
      "nhan_hang": [],
      "keywords_found": [],
      "crawl_timestamp": "2025-07-04T11:26:32.937223"
    },
    {
      "stt": 1,
      "ngay_phat_hanh": "2025-07-04",
      "dau_bao": "AFAMILY",
      "cum_noi_dung": "Khác",
      "tom_tat_noi_dung": "Không tìm thấy bài viết nào liên quan đến các từ khóa \"dầu thực vật\", \"Nakydaco\", \"Nortalic\", \"Coba\", \"dầu hướng dương\" trên website https://afamily.vn trong khoảng thời gian từ ngày 2025-05-04 đến ngày 2025-07-04.",
      "link_bai_bao": "https://afamily.vn",
      "nganh_hang": "Dầu ăn",
      "nhan_hang": [],
      "keywords_found": [],
      "crawl_timestamp": "2025-07-04T11:26:43.919904"
    },
    {
      "stt": 1,
      "ngay_phat_hanh": "2025-07-04",
      "dau_bao": "DOANHNHANSAIGON",
      "cum_noi_dung": "Khác",
      "tom_tat_noi_dung": "### 1. \n- **\n- **\n- **Tóm tắt:** Bài viết nêu bật lợi ích của dầu thực vật trong chế độ ăn uống, nhấn mạnh các sản phẩm chính từ Nakydaco và Coba.\n- **Link:** [Đọc thêm]",
      "link_bai_bao": "https://doanhnhansaigon.vn/tang-cuong-cham-soc-suc-khoe-tu-dau-thuc-vat",
      "nganh_hang": "Dầu ăn",
      "nhan_hang": [],
      "keywords_found": [],
      "crawl_timestamp": "2025-07-04T11:27:04.175708"
    },
    {
      "stt": 2,
      "ngay_phat_hanh": "2025-07-04",
      "dau_bao": "DOANHNHANSAIGON",
      "cum_noi_dung": "Khác",
      "tom_tat_noi_dung": "### 2. \n- **\n- **\n- **Tóm tắt:** Phân tích sự phát triển của thị trường dầu hướng dương với sự tham gia của các thương hiệu như Nortalic, dự báo xu hướng và thách thức.\n- **Link:** [Đọc thêm]",
      "link_bai_bao": "https://doanhnhansaigon.vn/xu-huong-thi-truong-dau-huong-duong",
      "nganh_hang": "Dầu ăn",
      "nhan_hang": [],
      "keywords_found": [],
      "crawl_timestamp": "2025-07-04T11:27:04.176713"
    }
  ],
  "generated_at": "2025-07-04T11:28:17.033220",
  "total_articles": 8,
  "date_range": "Từ ngày 04/05/2025 đến ngày 04/07/2025"
}